QuantSI/__init__.py
QuantSI/_version.py
QuantSI/allunits.py
QuantSI/conftest.py
QuantSI/constants.py
QuantSI/fundamentalunits.py
QuantSI/stdunits.py
QuantSI/tests/__init__.py
QuantSI/tests/test_units.py
QuantSI-0.1.dist-info/LICENSE
QuantSI-0.1.dist-info/METADATA
QuantSI-0.1.dist-info/WHEEL
QuantSI-0.1.dist-info/top_level.txt
QuantSI-0.1.dist-info/RECORD
